pitia/__init__.py
pitia/cli.py
pitia-0.1.0.dist-info/licenses/LICENSE
pitia-0.1.0.dist-info/METADATA
pitia-0.1.0.dist-info/WHEEL
pitia-0.1.0.dist-info/entry_points.txt
pitia-0.1.0.dist-info/top_level.txt
pitia-0.1.0.dist-info/RECORD
