Metadata-Version: 2.4
Name: pitia
Version: 0.1.0
Summary: Assistente virtual com memória e aprendizado contínuo
Author: Stayely
Author-email: lsszdst@gmail.com
Classifier: Programming Language :: Python :: 3
Classifier: License :: OSI Approved :: GNU General Public License v3 (GPLv3)
Classifier: Operating System :: OS Independent
Classifier: Natural Language :: Portuguese
Classifier: Topic :: Scientific/Engineering :: Artificial Intelligence
Requires-Python: >=3.8
License-File: LICENSE
Requires-Dist: requests>=4.13.4
Requires-Dist: beautifulsoup4>=2.0.3
Requires-Dist: google>=2.0.3
Requires-Dist: nltk>=3.9.1
Requires-Dist: sumy>=0.11.0
Requires-Dist: scikit-learn>=1.7.1
Requires-Dist: numpy>=1.20
Dynamic: author
Dynamic: author-email
Dynamic: classifier
Dynamic: description
Dynamic: description-content-type
Dynamic: license-file
Dynamic: requires-dist
Dynamic: requires-python
Dynamic: summary
